abhi_ore/__init__.py
abhi_ore/checker.py
abhi_ore-0.1.0.dist-info/licenses/LICENSE.txt
abhi_ore-0.1.0.dist-info/METADATA
abhi_ore-0.1.0.dist-info/WHEEL
abhi_ore-0.1.0.dist-info/top_level.txt
abhi_ore-0.1.0.dist-info/RECORD
