Metadata-Version: 2.4
Name: abhi-ore
Version: 0.1.0
Summary: A simple odd or even checking Python library
Author-email: Abhinav B Prasad <abhinavbprasad.11ab@gmail.com>
License: MIT
Project-URL: Homepage, https://github.com/Icyscar/abhi_ore
Requires-Python: >=3.7
License-File: LICENSE.txt
Dynamic: license-file
